color_mask/.python-version
color_mask/__init__.py
color_mask/color_mask.py
color_mask-0.1.0.dist-info/entry_points.txt
color_mask-0.1.0.dist-info/WHEEL
color_mask-0.1.0.dist-info/METADATA
color_mask-0.1.0.dist-info/RECORD
