Metadata-Version: 2.1
Name: color-mask
Version: 0.1.0
Summary: This library creates a color mask for an image and lets you download the masked image. To create a mask simply use command 'clrmsk createmsk <path of the image>. To save the mask simply use 'clrmsk savemsk <path of the image>.
Author: Your Name
Author-email: you@example.com
Requires-Python: >=3.8,<4.0
Classifier: Programming Language :: Python :: 3
Classifier: Programming Language :: Python :: 3.10
Classifier: Programming Language :: Python :: 3.8
Classifier: Programming Language :: Python :: 3.9
